MANIFEST.in
README.md
setup.py
django_clever_pages.egg-info/PKG-INFO
django_clever_pages.egg-info/SOURCES.txt
django_clever_pages.egg-info/dependency_links.txt
django_clever_pages.egg-info/not-zip-safe
django_clever_pages.egg-info/requires.txt
django_clever_pages.egg-info/top_level.txt
page/__init__.py
page/admin.py
page/models.py
page/search_indexes.py
page/urls.py
page/views.py
page/migrations/0001_initial.py
page/migrations/0002_add_meta_tag_fields.py
page/migrations/__init__.py
page/templates/page/default.html
page/templates/page/homepage.html
page/templates/search/indexes/page/page_text.txt
page/templatetags/__init__.py
page/templatetags/page_tags.py
page/tests/__init__.py
page/tests/test_models.py
page/tests/test_views.py