Metadata-Version: 1.1
Name: django-clever-pages
Version: 0.3.1
Summary: App for create pages
Home-page: https://github.com/artofhuman/django-clever-pages
Author: Pupkov Semyon
Author-email: semen.pupkov@gmail.com
License: UNKNOWN
Platform: UNKNOWN
Classifier: Development Status :: 5 - Production/Stable
Classifier: Intended Audience :: Developers
Classifier: Environment :: Web Environment
Classifier: Framework :: Django
Classifier: Operating System :: OS Independent
Classifier: Programming Language :: Python
Classifier: Programming Language :: Python 2.7
Classifier: Programming Language :: Python :: 3
